trophy/__init__.py
trophy/client.py
trophy/environment.py
trophy/achievements/__init__.py
trophy/achievements/client.py
trophy/achievements/raw_client.py
trophy/admin/__init__.py
trophy/admin/client.py
trophy/admin/raw_client.py
trophy/admin/streaks/__init__.py
trophy/admin/streaks/client.py
trophy/admin/streaks/raw_client.py
trophy/admin/streaks/freezes/__init__.py
trophy/admin/streaks/freezes/client.py
trophy/admin/streaks/freezes/raw_client.py
trophy/admin/streaks/freezes/types/__init__.py
trophy/admin/streaks/freezes/types/create_streak_freezes_request_freezes_item.py
trophy/admin/streaks/types/__init__.py
trophy/admin/streaks/types/restore_streaks_request_users_item.py
trophy/core/__init__.py
trophy/core/api_error.py
trophy/core/client_wrapper.py
trophy/core/datetime_utils.py
trophy/core/file.py
trophy/core/force_multipart.py
trophy/core/http_client.py
trophy/core/http_response.py
trophy/core/jsonable_encoder.py
trophy/core/pydantic_utilities.py
trophy/core/query_encoder.py
trophy/core/remove_none_from_dict.py
trophy/core/request_options.py
trophy/core/serialization.py
trophy/errors/__init__.py
trophy/errors/bad_request_error.py
trophy/errors/not_found_error.py
trophy/errors/unauthorized_error.py
trophy/errors/unprocessable_entity_error.py
trophy/leaderboards/__init__.py
trophy/leaderboards/client.py
trophy/leaderboards/raw_client.py
trophy/leaderboards/types/__init__.py
trophy/leaderboards/types/leaderboards_all_response_item.py
trophy/leaderboards/types/leaderboards_all_response_item_status.py
trophy/metrics/__init__.py
trophy/metrics/client.py
trophy/metrics/raw_client.py
trophy/points/__init__.py
trophy/points/client.py
trophy/points/raw_client.py
trophy/streaks/__init__.py
trophy/streaks/client.py
trophy/streaks/raw_client.py
trophy/streaks/types/__init__.py
trophy/streaks/types/streaks_rankings_request_type.py
trophy/types/__init__.py
trophy/types/achievement_completion_response.py
trophy/types/achievement_response.py
trophy-1.0.42.dist-info/licenses/LICENSE
trophy-1.0.42.dist-info/METADATA
trophy-1.0.42.dist-info/WHEEL
trophy-1.0.42.dist-info/top_level.txt
trophy-1.0.42.dist-info/RECORD
