Metadata-Version: 2.4
Name: trophy
Version: 1.0.42
Summary: A Python library for the Trophy API
License: MIT
Project-URL: Homepage, https://github.com/trophyso/trophy-python
Project-URL: Repository, https://github.com/trophyso/trophy-python
License-File: LICENSE
Requires-Dist: requests
Requires-Dist: httpx
Requires-Dist: pydantic
Requires-Dist: typing
Requires-Dist: dataclasses
Requires-Dist: typing_extensions
Dynamic: license-file
